TabulaScan/__init__.py
TabulaScan-0.2.0.dist-info/LICENSE
TabulaScan-0.2.0.dist-info/METADATA
TabulaScan-0.2.0.dist-info/WHEEL
TabulaScan-0.2.0.dist-info/top_level.txt
TabulaScan-0.2.0.dist-info/RECORD
