Metadata-Version: 2.1
Name: TabulaScan
Version: 0.2.0
Summary: Streamlined Scanned Image Table Extraction and Excel Conversion
Home-page: https://github.com/oussama95boussaid/TabulaScan
Author: Oussama Boussaid
Author-email: oussama.bouss3id95@gmail.com
Classifier: Programming Language :: Python :: 3
Classifier: License :: OSI Approved :: MIT License
Classifier: Operating System :: OS Independent
Requires-Python: >=3.7
License-File: LICENSE
Requires-Dist: numpy
Requires-Dist: pandas
Requires-Dist: opencv-python
Requires-Dist: ultralyticsplus ==0.0.23
Requires-Dist: ultralytics ==8.0.21
Requires-Dist: paddlepaddle
Requires-Dist: paddleocr
Requires-Dist: tensorflow
Requires-Dist: Pillow
